mcap_ros2idl_support/__init__.py
mcap_ros2idl_support/decode_factory.py
mcap_ros2idl_support/cdr/__init__.py
mcap_ros2idl_support/cdr/encapsulation_kind.py
mcap_ros2idl_support/cdr/get_encapsulation_kind_info.py
mcap_ros2idl_support/cdr/is_big_endian.py
mcap_ros2idl_support/cdr/length_codes.py
mcap_ros2idl_support/cdr/reader.py
mcap_ros2idl_support/cdr/reserved_pids.py
mcap_ros2idl_support/cdr/size_calculator.py
mcap_ros2idl_support/cdr/writer.py
mcap_ros2idl_support/message_definition/__init__.py
mcap_ros2idl_support/message_definition/py.typed
mcap_ros2idl_support/omgidl_parser/__init__.py
mcap_ros2idl_support/omgidl_parser/parse.py
mcap_ros2idl_support/omgidl_parser/process.py
mcap_ros2idl_support/omgidl_parser/py.typed
mcap_ros2idl_support/ros2idl_parser/__init__.py
mcap_ros2idl_support/ros2idl_parser/parse.py
mcap_ros2idl_support/ros2idl_parser/py.typed
mcap_ros2idl_support/rosmsg/__init__.py
mcap_ros2idl_support/rosmsg/md5.py
mcap_ros2idl_support/rosmsg/parse.py
mcap_ros2idl_support/rosmsg/stringify.py
mcap_ros2idl_support/rosmsg2_serialization/__init__.py
mcap_ros2idl_support/rosmsg2_serialization/message_definition_has_data_fields.py
mcap_ros2idl_support/rosmsg2_serialization/message_reader.py
mcap_ros2idl_support/rosmsg2_serialization/message_writer.py
mcap_ros2idl_support/rostime/__init__.py
mcap_ros2idl_support-0.1.2.dist-info/licenses/LICENSE
mcap_ros2idl_support-0.1.2.dist-info/METADATA
mcap_ros2idl_support-0.1.2.dist-info/WHEEL
mcap_ros2idl_support-0.1.2.dist-info/top_level.txt
mcap_ros2idl_support-0.1.2.dist-info/RECORD
