Metadata-Version: 2.4
Name: mcap-ros2idl-support
Version: 0.1.2
Summary: A Python library to read and parse ROS 2 MCAP bag files without a ROS 2 runtime.
Author: dskkato
License: MIT License
Classifier: Programming Language :: Python :: 3
Classifier: Programming Language :: Python :: 3.10
Classifier: Programming Language :: Python :: 3.11
Classifier: Programming Language :: Python :: 3.12
Classifier: Programming Language :: Python :: 3.13
Classifier: License :: OSI Approved :: MIT License
Classifier: Operating System :: OS Independent
Requires-Python: >=3.10
License-File: LICENSE
Requires-Dist: mcap>=1.3.0
Requires-Dist: lark
Requires-Dist: typing-extensions
Provides-Extra: dev
Requires-Dist: pre-commit; extra == "dev"
Requires-Dist: pytest; extra == "dev"
Requires-Dist: maturin<2,>=1.5; extra == "dev"
Requires-Dist: build; extra == "dev"
Dynamic: license-file
